genjax/__init__.py
genjax/_src/__init__.py
genjax/_src/adev/__init__.py
genjax/_src/adev/core.py
genjax/_src/adev/primitives.py
genjax/_src/checkify.py
genjax/_src/core/__init__.py
genjax/_src/core/compiler/__init__.py
genjax/_src/core/compiler/initial_style_primitive.py
genjax/_src/core/compiler/interpreters/__init__.py
genjax/_src/core/compiler/interpreters/environment.py
genjax/_src/core/compiler/interpreters/incremental.py
genjax/_src/core/compiler/interpreters/stateful.py
genjax/_src/core/compiler/interpreters/time_travel.py
genjax/_src/core/compiler/staging.py
genjax/_src/core/generative/__init__.py
genjax/_src/core/generative/choice_map.py
genjax/_src/core/generative/concepts.py
genjax/_src/core/generative/functional_types.py
genjax/_src/core/generative/generative_function.py
genjax/_src/core/generative/requests.py
genjax/_src/core/pytree.py
genjax/_src/core/typing.py
genjax/_src/generative_functions/__init__.py
genjax/_src/generative_functions/combinators/__init__.py
genjax/_src/generative_functions/combinators/dimap.py
genjax/_src/generative_functions/combinators/mask.py
genjax/_src/generative_functions/combinators/mixture.py
genjax/_src/generative_functions/combinators/or_else.py
genjax/_src/generative_functions/combinators/repeat.py
genjax/_src/generative_functions/combinators/scan.py
genjax/_src/generative_functions/combinators/switch.py
genjax/_src/generative_functions/combinators/vmap.py
genjax/_src/generative_functions/distributions/__init__.py
genjax/_src/generative_functions/distributions/custom/__init__.py
genjax/_src/generative_functions/distributions/custom/discrete_hmm.py
genjax/_src/generative_functions/distributions/distribution.py
genjax/_src/generative_functions/distributions/tensorflow_probability/__init__.py
genjax/_src/generative_functions/static.py
genjax/_src/inference/__init__.py
genjax/_src/inference/exact_testbed.py
genjax/_src/inference/requests/__init__.py
genjax/_src/inference/requests/hmc.py
genjax-0.10.3.dist-info/LICENSE
genjax-0.10.3.dist-info/METADATA
genjax-0.10.3.dist-info/WHEEL
genjax-0.10.3.dist-info/RECORD
